[
null,
{"id":1,"animationId":0,"consumable":true,"damage":{"critical":false,"elementId":0,"formula":"0","type":0,"variance":20},"description":"以下是當開啟選單時，想顯示道具\n上方的恢復道具欄位。","effects":[],"hitType":0,"iconIndex":0,"itypeId":1,"name":"-----已預留","note":"","occasion":3,"price":0,"repeats":1,"scope":7,"speed":0,"successRate":100,"tpGain":0},
{"id":2,"animationId":35,"consumable":false,"damage":{"critical":false,"elementId":0,"formula":"0","type":0,"variance":20},"description":"可用以撲滅一層樓的火\n(似乎可以用來開啟某處的逃生門?!)","effects":[],"hitType":0,"iconIndex":64,"itypeId":2,"name":"滅火器","note":"","occasion":0,"price":20,"repeats":1,"scope":0,"speed":0,"successRate":100,"tpGain":0},
{"id":3,"animationId":48,"consumable":false,"damage":{"critical":false,"elementId":0,"formula":"0","type":0,"variance":20},"description":"可用以尋找<迷失的小孩>交換情報\n似乎還有其他用途","effects":[],"hitType":0,"iconIndex":224,"itypeId":2,"name":"棒棒糖","note":"","occasion":0,"price":10,"repeats":1,"scope":7,"speed":0,"successRate":100,"tpGain":0},
{"id":4,"animationId":0,"consumable":true,"damage":{"critical":false,"elementId":0,"formula":"0","type":0,"variance":20},"description":"上面寫著：1995年9月23日, \nVietnam多元二手雜貨店正式進駐第一廣場大樓!","effects":[],"hitType":0,"iconIndex":192,"itypeId":2,"name":"雜貨店宣傳單","note":"","occasion":0,"price":0,"repeats":1,"scope":7,"speed":0,"successRate":100,"tpGain":0},
{"id":5,"animationId":0,"consumable":true,"damage":{"critical":false,"elementId":0,"formula":"0","type":0,"variance":20},"description":"上面寫著:盡快逃出去！不然就來不及了！","effects":[],"hitType":0,"iconIndex":194,"itypeId":2,"name":"奇怪的字條","note":"","occasion":0,"price":2,"repeats":1,"scope":7,"speed":0,"successRate":100,"tpGain":0},
{"id":6,"animationId":0,"consumable":false,"damage":{"critical":false,"elementId":0,"formula":"0","type":0,"variance":20},"description":"似乎是修女平常用來祈禱的書籍","effects":[],"hitType":0,"iconIndex":121,"itypeId":2,"name":"聖典","note":"","occasion":3,"price":0,"repeats":1,"scope":7,"speed":0,"successRate":100,"tpGain":0},
{"id":7,"animationId":41,"consumable":false,"damage":{"critical":false,"elementId":0,"formula":"0","type":0,"variance":20},"description":"處方簽上寫著長期焦慮、憂鬱患者適用","effects":[],"hitType":0,"iconIndex":166,"itypeId":2,"name":"精神藥物","note":"","occasion":0,"price":100,"repeats":1,"scope":7,"speed":0,"successRate":100,"tpGain":0},
{"id":8,"animationId":0,"consumable":false,"damage":{"critical":false,"elementId":0,"formula":"0","type":0,"variance":20},"description":"女友媽媽的精神診斷證明, 寫著該患者長期患有焦慮及憂鬱症","effects":[],"hitType":0,"iconIndex":207,"itypeId":2,"name":"林鳳的精神診斷書","note":"","occasion":0,"price":0,"repeats":1,"scope":7,"speed":0,"successRate":100,"tpGain":0},
{"id":9,"animationId":0,"consumable":true,"damage":{"critical":false,"elementId":0,"formula":"0","type":0,"variance":20},"description":"上面標記著樓層號碼: 10F","effects":[],"hitType":0,"iconIndex":306,"itypeId":2,"name":"故障的灑水器","note":"","occasion":0,"price":2,"repeats":1,"scope":7,"speed":0,"successRate":100,"tpGain":0},
{"id":10,"animationId":0,"consumable":true,"damage":{"critical":false,"elementId":0,"formula":"0","type":0,"variance":20},"description":"貼有2F服飾店LOGO的紙箱","effects":[],"hitType":0,"iconIndex":274,"itypeId":2,"name":"未拆封的紙箱","note":"","occasion":0,"price":3,"repeats":1,"scope":7,"speed":0,"successRate":100,"tpGain":0},
{"id":11,"animationId":0,"consumable":false,"damage":{"critical":false,"elementId":0,"formula":"0","type":0,"variance":20},"description":"似乎可以拿來當開啟某處暗門的鑰匙","effects":[],"hitType":0,"iconIndex":188,"itypeId":2,"name":"墨孟洋的證件","note":"","occasion":0,"price":0,"repeats":1,"scope":7,"speed":0,"successRate":100,"tpGain":0},
{"id":12,"animationId":0,"consumable":false,"damage":{"critical":false,"elementId":0,"formula":"0","type":0,"variance":20},"description":"藍紫色的鑰匙,好像是阿凌的東西","effects":[],"hitType":0,"iconIndex":292,"itypeId":2,"name":"6F樓梯間鑰匙","note":"","occasion":0,"price":0,"repeats":1,"scope":7,"speed":0,"successRate":100,"tpGain":0},
{"id":13,"animationId":0,"consumable":true,"damage":{"critical":false,"elementId":0,"formula":"0","type":0,"variance":20},"description":"不知道是誰抽完後亂丟在地上,是七星牌的!","effects":[],"hitType":0,"iconIndex":202,"itypeId":2,"name":"只剩一半的菸蒂","note":"","occasion":0,"price":1,"repeats":1,"scope":7,"speed":0,"successRate":100,"tpGain":0},
{"id":14,"animationId":0,"consumable":false,"damage":{"critical":false,"elementId":0,"formula":"0","type":0,"variance":20},"description":"上面寫著\"一人一票\"","effects":[],"hitType":0,"iconIndex":196,"itypeId":2,"name":"門票","note":"","occasion":0,"price":50,"repeats":1,"scope":7,"speed":0,"successRate":100,"tpGain":0},
{"id":15,"animationId":0,"consumable":true,"damage":{"critical":false,"elementId":0,"formula":"0","type":0,"variance":20},"description":"上面標註日期已經過期快兩年了,\n不是應該在每年消防檢查時被換新嗎....","effects":[],"hitType":0,"iconIndex":68,"itypeId":2,"name":"過期滅火器","note":"","occasion":0,"price":5,"repeats":1,"scope":7,"speed":0,"successRate":100,"tpGain":0},
{"id":16,"animationId":0,"consumable":true,"damage":{"critical":false,"elementId":0,"formula":"0","type":0,"variance":20},"description":"每年六月都會進行大樓檢查","effects":[],"hitType":0,"iconIndex":187,"itypeId":2,"name":"大樓檢查報告","note":"","occasion":0,"price":5,"repeats":1,"scope":7,"speed":0,"successRate":100,"tpGain":0},
{"id":17,"animationId":0,"consumable":true,"damage":{"critical":false,"elementId":0,"formula":"0","type":0,"variance":20},"description":"似乎有人在蒐集這個?","effects":[],"hitType":0,"iconIndex":180,"itypeId":2,"name":"空酒瓶","note":"","occasion":0,"price":10,"repeats":1,"scope":7,"speed":0,"successRate":100,"tpGain":0},
{"id":18,"animationId":0,"consumable":true,"damage":{"critical":false,"elementId":0,"formula":"0","type":0,"variance":20},"description":"\"看起來\"可愛、穿著黃色外套....似乎是某人的遺失物品","effects":[],"hitType":0,"iconIndex":1,"itypeId":2,"name":"\"丟失的\"娃娃","note":"","occasion":0,"price":25,"repeats":1,"scope":7,"speed":0,"successRate":100,"tpGain":0},
{"id":19,"animationId":0,"consumable":false,"damage":{"critical":false,"elementId":0,"formula":"0","type":0,"variance":20},"description":"可以用來開啟旅店儲藏室，但只能暫時借用","effects":[],"hitType":0,"iconIndex":195,"itypeId":2,"name":"旅店儲藏室的鑰匙","note":"","occasion":0,"price":0,"repeats":1,"scope":7,"speed":0,"successRate":100,"tpGain":0},
{"id":20,"animationId":0,"consumable":false,"damage":{"critical":false,"elementId":0,"formula":"0","type":0,"variance":20},"description":"採用以物易物、資訊蒐集的方式進行遊戲。(可留意前後不同之處，敬請享受遊戲！)","effects":[],"hitType":0,"iconIndex":193,"itypeId":2,"name":"遊戲進行提示","note":"","occasion":0,"price":0,"repeats":1,"scope":7,"speed":0,"successRate":100,"tpGain":0},
{"id":21,"animationId":0,"consumable":false,"damage":{"critical":false,"elementId":0,"formula":"0","type":0,"variance":20},"description":"是一個奇怪的老伯伯研發的藥劑,似乎只有他知道怎麼用","effects":[],"hitType":0,"iconIndex":178,"itypeId":2,"name":"滅火器的更換藥劑","note":"","occasion":0,"price":0,"repeats":1,"scope":7,"speed":0,"successRate":100,"tpGain":0},
{"id":22,"animationId":0,"consumable":true,"damage":{"critical":false,"elementId":0,"formula":"0","type":0,"variance":20},"description":"上面的人...好眼熟....","effects":[],"hitType":0,"iconIndex":244,"itypeId":2,"name":"雙人的大頭照","note":"","occasion":0,"price":10,"repeats":1,"scope":7,"speed":0,"successRate":100,"tpGain":0},
{"id":23,"animationId":0,"consumable":true,"damage":{"critical":false,"elementId":0,"formula":"0","type":0,"variance":20},"description":"上面寫著：尋找門票，也許可以改變一個人的命運","effects":[],"hitType":0,"iconIndex":194,"itypeId":2,"name":"奇怪的字條-4","note":"","occasion":0,"price":2,"repeats":1,"scope":7,"speed":0,"successRate":100,"tpGain":0},
{"id":24,"animationId":0,"consumable":true,"damage":{"critical":false,"elementId":0,"formula":"0","type":0,"variance":20},"description":"上面寫著: 搭上逃生小船，才能離開這一場大火","effects":[],"hitType":0,"iconIndex":194,"itypeId":2,"name":"奇怪的字條-2","note":"","occasion":0,"price":2,"repeats":1,"scope":7,"speed":0,"successRate":100,"tpGain":0},
{"id":25,"animationId":0,"consumable":true,"damage":{"critical":false,"elementId":0,"formula":"0","type":0,"variance":20},"description":"上面寫著: 衛爾康西餐廳","effects":[],"hitType":0,"iconIndex":194,"itypeId":2,"name":"奇怪的字條-3","note":"","occasion":0,"price":2,"repeats":1,"scope":7,"speed":0,"successRate":100,"tpGain":0},
{"id":26,"animationId":0,"consumable":true,"damage":{"critical":false,"elementId":0,"formula":"0","type":0,"variance":20},"description":"小女孩可可的玩具積木","effects":[],"hitType":0,"iconIndex":306,"itypeId":2,"name":"可可的積木","note":"","occasion":0,"price":0,"repeats":1,"scope":7,"speed":0,"successRate":100,"tpGain":0},
{"id":27,"animationId":0,"consumable":true,"damage":{"critical":false,"elementId":0,"formula":"0","type":0,"variance":20},"description":"","effects":[],"hitType":0,"iconIndex":0,"itypeId":1,"name":"","note":"","occasion":0,"price":0,"repeats":1,"scope":7,"speed":0,"successRate":100,"tpGain":0},
{"id":28,"animationId":0,"consumable":true,"damage":{"critical":false,"elementId":0,"formula":"0","type":0,"variance":20},"description":"","effects":[],"hitType":0,"iconIndex":0,"itypeId":1,"name":"","note":"","occasion":0,"price":0,"repeats":1,"scope":7,"speed":0,"successRate":100,"tpGain":0},
{"id":29,"animationId":0,"consumable":true,"damage":{"critical":false,"elementId":0,"formula":"0","type":0,"variance":20},"description":"","effects":[],"hitType":0,"iconIndex":0,"itypeId":1,"name":"","note":"","occasion":0,"price":0,"repeats":1,"scope":7,"speed":0,"successRate":100,"tpGain":0},
{"id":30,"animationId":0,"consumable":true,"damage":{"critical":false,"elementId":0,"formula":"0","type":0,"variance":20},"description":"","effects":[],"hitType":0,"iconIndex":0,"itypeId":1,"name":"","note":"","occasion":0,"price":0,"repeats":1,"scope":7,"speed":0,"successRate":100,"tpGain":0}
]